MANIFEST.in
README.rst
setup.json
setup.py
command_tree/__init__.py
command_tree/argument.py
command_tree/command_tree.py
command_tree/config.py
command_tree/doc_string_parser.py
command_tree/exceptions.py
command_tree/groups.py
command_tree/item.py
command_tree/leaf.py
command_tree/node.py
command_tree/types.py
command_tree.egg-info/PKG-INFO
command_tree.egg-info/SOURCES.txt
command_tree.egg-info/dependency_links.txt
command_tree.egg-info/top_level.txt
test/test_build.py
test/test_build_common_argument.py
test/test_build_configurable_features.py
test/test_build_exceptions.py
test/test_build_groups.py
test/test_default_handling.py
test/test_doc_string_parse.py
test/test_examples.py
test/test_google_doc_string_parser.py
test/test_handler_parent.py
test/test_node_external_items.py
test/test_node_handler.py
test/test_types.py